biblelib/__init__.py
biblelib/book/ReadMe.md
biblelib/book/__init__.py
biblelib/book/book.py
biblelib/book/books.tsv
biblelib/corpus/eng/BSB/__init__.py
biblelib/corpus/eng/BSB/corpus.py
biblelib/sources.py
biblelib/unit/__init__.py
biblelib/unit/book.py
biblelib/unit/bookchapters.tsv
biblelib/unit/chapter.py
biblelib/unit/chapters.tsv
biblelib/unit/chapterverses.tsv
biblelib/unit/pericope.py
biblelib/unit/tempchapter.py
biblelib/unit/unit.py
biblelib/unit/unitrange.py
biblelib/unit/verse.py
biblelib/versification/Enumerator.py
biblelib/versification/Mapper.py
biblelib/versification/ReadMe.md
biblelib/versification/VrefReader.py
biblelib/versification/__init__.py
biblelib/versification/eng-nt-vref.txt
biblelib/versification/eng-ot-vref.txt
biblelib/versification/eng-protestant-vref.txt
biblelib/versification/org-nt-vref.txt
biblelib/versification/org-ot-vref.txt
biblelib/versification/org-protestant-vref.txt
biblelib/versification/rso-nt-vref.txt
biblelib/versification/rso-ot-vref.txt
biblelib/versification/rso-protestant-vref.txt
biblelib/word/__init__.py
biblelib/word/bcvwpid.py
biblelib/word/mappings/__init__.py
biblelib/word/mappings/gnt.py
biblelib/word/mappings/marble.py
biblelib/word/mappings/wlcm.py
biblelib/word/ubs.py
biblelib/word/urlmanager.py
biblelib-0.3.29.dist-info/METADATA
biblelib-0.3.29.dist-info/WHEEL
biblelib-0.3.29.dist-info/licenses/LICENSE.md
biblelib-0.3.29.dist-info/licenses/LICENSE.md~
biblelib-0.3.29.dist-info/RECORD
