Metadata-Version: 2.4
Name: biblelib
Version: 0.3.29
Summary: Utilities for working with metadata for Bible books, references, pericopes, and other units.
License-File: LICENSE.md
License-File: LICENSE.md~
Author: Sean Boisen
Author-email: sean.boisen@gmail.com
Requires-Python: >=3.9,<3.14
Classifier: Operating System :: OS Independent
Classifier: Programming Language :: Python :: 3
Classifier: Programming Language :: Python :: 3.9
Classifier: Programming Language :: Python :: 3.10
Classifier: Programming Language :: Python :: 3.11
Classifier: Programming Language :: Python :: 3.12
Classifier: Programming Language :: Python :: 3.13
Classifier: Programming Language :: Python :: 3.6
Requires-Dist: pydantic (>=2.3.0,<3.0.0)
Requires-Dist: requests (>=2,<3)
Project-URL: Repository, https://github.com/Clear-Bible/Biblelib/
